{
    "title": "Collection of loaders",
    "date": "2017-11-06",
    "tags": ["html", "css", "animation", "codepen"],
    "thumb": "6147ab361a09aa3e315924cc1517ed57",
    "content": [
        "Here are three of my CSS loaders, which I didn't share on my website previously. The first one uses the standard gooey SVG filter on the seven moving dots, the second is the simple cube with animated backgrounds and the last animation consists of the circles changing their sizes like waves. Nothing serious, but they can look very attractive.",
        ["codepen", "NpZbJL"],
        ["codepen", "MmJggp"],
        ["codepen", "RpXEjE"]
    ]
}
